{"authorDailyContributionsMap":{"aditichadha1310":[{"date":"2021-08-19","commitResults":[{"hash":"a348f6e90d7f87f77630da29a2d9300ba754d387","messageTitle":"Level-0","messageBody":"","fileTypesAndContributionMap":{"java":{"insertions":3,"deletions":0}}}]},{"date":"2021-08-24","commitResults":[{"hash":"790db41105d6b95dfba6739f6b4308fb8a8c23de","messageTitle":"Level-1","messageBody":"Greet, Echo, Exit\n","fileTypesAndContributionMap":{"java":{"insertions":23,"deletions":6}}}]}]},"authorFileTypeContributionMap":{"aditichadha1310":{"java":26,"md":0,"fxml":0,"sh":0,"bat":0,"gradle":0,"txt":0}},"authorContributionVariance":{"aditichadha1310":3.8080513},"authorDisplayNameMap":{"aditichadha1310":"ADIT..ADHA"}}
