{"authorDailyContributionsMap":{"Dniv-ra":[{"date":"2021-08-21","commitResults":[{"hash":"987f2204048f06288fea16240a0cc6f008d9b17f","messageTitle":"Implement greet","messageBody":"","tags":["Level-0"],"fileTypesAndContributionMap":{"java":{"insertions":8,"deletions":1}}},{"hash":"499c6bf1e05db174e27b04db90994370b6f50f43","messageTitle":"Implement echo","messageBody":"","tags":["Level-1"],"fileTypesAndContributionMap":{"java":{"insertions":19,"deletions":10}}},{"hash":"8dd95f1ec191d116ec7a5f798b9e0433d641fa95","messageTitle":"Implement add and list","messageBody":"","tags":["Level-2"],"fileTypesAndContributionMap":{"java":{"insertions":17,"deletions":3}}}]},{"date":"2021-08-24","commitResults":[{"hash":"69601b34686b7403832ad8118dee4f23adbb9893","messageTitle":"Implement marking as complete","messageBody":"","tags":["Level-3"],"fileTypesAndContributionMap":{"java":{"insertions":37,"deletions":5}}}]}]},"authorFileTypeContributionMap":{"Dniv-ra":{"java":68,"md":0,"fxml":0,"sh":0,"bat":0,"gradle":0,"txt":0}},"authorContributionVariance":{"Dniv-ra":22.896193},"authorDisplayNameMap":{"Dniv-ra":"SRID..ASAN"}}
