{"authorDailyContributionsMap":{"irvinseet":[{"date":"2021-08-19","commitResults":[{"hash":"491a437094ef5e8910c6f40391cc26e29cff9b6e","messageTitle":"Level-0","messageBody":"","fileTypesAndContributionMap":{"java":{"insertions":8,"deletions":6}}},{"hash":"9a6e90af4465968c6e684a067c8f10887552395c","messageTitle":"Level-0","messageBody":"","tags":["Level-0"],"fileTypesAndContributionMap":{"java":{"insertions":6,"deletions":8}}}]},{"date":"2021-08-22","commitResults":[{"hash":"a77a2c0ea99b9d9b52a12f20d79fcafa13715b73","messageTitle":"Level-1","messageBody":"Implement echo on user input, exits on \"bye\"\n","fileTypesAndContributionMap":{"java":{"insertions":24,"deletions":2}}},{"hash":"cd632d2fd6c56129ae5ff4345391e399e0232dcb","messageTitle":"Level-1","messageBody":"Implement echo on user input, exits on \"bye\"\n","tags":["Level-1"],"fileTypesAndContributionMap":{"java":{"insertions":1,"deletions":1}}},{"hash":"4e8de3afa1000db59f1f29eea71036d64f541998","messageTitle":"Level-2","messageBody":"Add user input into a todolist, return list when user inputs \"list\"\n","tags":["Level-2"],"fileTypesAndContributionMap":{"java":{"insertions":17,"deletions":1}}},{"hash":"44f801c30326266a2062c62364df42dad0152ec8","messageTitle":"Level-3","messageBody":"Add the ability to mark tasks as done.\nAdd Task Class\n","fileTypesAndContributionMap":{"java":{"insertions":15,"deletions":3}}},{"hash":"bc75e896b5a1eb02b0ede6323f76de434f34827e","messageTitle":"Level-3","messageBody":"Add the ability to mark tasks as done.\nAdd Task Class\n","tags":["Level-3"],"fileTypesAndContributionMap":{"java":{"insertions":22,"deletions":0}}},{"hash":"8ac9ace82053cd6421b16447b5407cd161174945","messageTitle":"A-CodingStandard","messageBody":"*Indentation and spacing\n*markAsDone refactor to setDone\n*todolist refactor to tasks\n*Add comments\n","tags":["A-CodingStandard"],"fileTypesAndContributionMap":{"java":{"insertions":15,"deletions":11}}}]},{"date":"2021-08-30","commitResults":[{"hash":"dbcbabdec72787e013558df50001fa6176f32d22","messageTitle":"changes","messageBody":"","fileTypesAndContributionMap":{"java":{"insertions":7,"deletions":10}}}]},{"date":"2021-08-31","commitResults":[{"hash":"3178f354dcf57bd7cbd2b622386b971e8a568878","messageTitle":"Level-4, A-CodeQuality","messageBody":"","tags":["Level-4","A-CodeQuality"],"fileTypesAndContributionMap":{"java":{"insertions":206,"deletions":43}}}]},{"date":"2021-09-04","commitResults":[{"hash":"7612928488fe4d43148dcb274691611d8659eda2","messageTitle":"Level-5 Error Handling. Introduce TaskManager class to handle user requests","messageBody":"","tags":["Level-5"],"fileTypesAndContributionMap":{"java":{"insertions":141,"deletions":146}}},{"hash":"bfa0fb4ab5e539e5607c88e1237caa74019f7602","messageTitle":"A-Packages. Put all classes in package \"duke\". Further refactor task and different task types into package \"duke/task\"","messageBody":"","fileTypesAndContributionMap":{"java":{"insertions":33,"deletions":11},"md":{"insertions":2,"deletions":2}}},{"hash":"b8cf0452eb8af0e1d43bbb4bf91494fee281a5c4","messageTitle":"Fixed some naming issues that arised from refactoring packages.","messageBody":"","tags":["A-Packages"],"fileTypesAndContributionMap":{"java":{"insertions":7,"deletions":7}}},{"hash":"6c40239e1c7398f64fb940e703083debe8db46b8","messageTitle":"Autoformatting and add new lines to end of some files","messageBody":"","fileTypesAndContributionMap":{"java":{"insertions":17,"deletions":23}}}]},{"date":"2021-09-07","commitResults":[{"hash":"4239ae2f83577f47ba5d4738d9e5825520833a6f","messageTitle":"Create InvalidCommandExpcetion, extract error messages","messageBody":"","fileTypesAndContributionMap":{"java":{"insertions":25,"deletions":18}}},{"hash":"6b34911a36ced0becc7cac303dc9d245027e5b48","messageTitle":"Change exceptions to user-created exceptions. -DukeException for valid command but incorrect description - InvalidCommandException for invalid command","messageBody":"","fileTypesAndContributionMap":{"java":{"insertions":40,"deletions":33}}}]}]},"authorFileTypeContributionMap":{"irvinseet":{"java":268,"md":2,"fxml":0,"sh":0,"bat":0,"gradle":0,"txt":0}},"authorContributionVariance":{"irvinseet":1003.722},"authorDisplayNameMap":{"irvinseet":"CS2113T-W11-2 SEET..RVIN"}}
