[{"path":"src/main/java/Duke.java","fileType":"java","lines":[{"lineNumber":1,"author":{"gitId":"gavienwz"},"content":"import java.util.Scanner;","lastModifiedDate":"2021-08-24"},{"lineNumber":2,"author":{"gitId":"gavienwz"},"content":"","lastModifiedDate":"2021-08-24"},{"lineNumber":3,"author":{"gitId":"-"},"content":"public class Duke {","lastModifiedDate":"2019-07-29"},{"lineNumber":4,"author":{"gitId":"gavienwz"},"content":"    private static Task[] tasks \u003d new Task[100];","lastModifiedDate":"2021-08-24"},{"lineNumber":5,"author":{"gitId":"gavienwz"},"content":"    private static int taskCount \u003d 0;","lastModifiedDate":"2021-08-24"},{"lineNumber":6,"author":{"gitId":"gavienwz"},"content":"","lastModifiedDate":"2021-08-24"},{"lineNumber":7,"author":{"gitId":"gavienwz"},"content":"    public static void printList() {","lastModifiedDate":"2021-08-24"},{"lineNumber":8,"author":{"gitId":"gavienwz"},"content":"        Task current;","lastModifiedDate":"2021-08-24"},{"lineNumber":9,"author":{"gitId":"gavienwz"},"content":"        String line \u003d \"____________________________________________________________\\n\";","lastModifiedDate":"2021-08-24"},{"lineNumber":10,"author":{"gitId":"gavienwz"},"content":"        System.out.print(line);","lastModifiedDate":"2021-08-24"},{"lineNumber":11,"author":{"gitId":"gavienwz"},"content":"        for (int i \u003d 0; i \u003c taskCount; i++) {","lastModifiedDate":"2021-08-24"},{"lineNumber":12,"author":{"gitId":"gavienwz"},"content":"            current \u003d tasks[i];","lastModifiedDate":"2021-08-24"},{"lineNumber":13,"author":{"gitId":"gavienwz"},"content":"            System.out.println(\" \" + (i + 1) + \".[\" + current.getStatusIcon() + \"] \" + current.description);","lastModifiedDate":"2021-08-24"},{"lineNumber":14,"author":{"gitId":"gavienwz"},"content":"        }","lastModifiedDate":"2021-08-24"},{"lineNumber":15,"author":{"gitId":"gavienwz"},"content":"        System.out.println(line);","lastModifiedDate":"2021-08-24"},{"lineNumber":16,"author":{"gitId":"gavienwz"},"content":"    }","lastModifiedDate":"2021-08-24"},{"lineNumber":17,"author":{"gitId":"-"},"content":"    public static void main(String[] args) {","lastModifiedDate":"2019-07-29"},{"lineNumber":18,"author":{"gitId":"-"},"content":"        String logo \u003d \" ____        _        \\n\"","lastModifiedDate":"2019-07-29"},{"lineNumber":19,"author":{"gitId":"-"},"content":"                + \"|  _ \\\\ _   _| | _____ \\n\"","lastModifiedDate":"2019-07-29"},{"lineNumber":20,"author":{"gitId":"-"},"content":"                + \"| | | | | | | |/ / _ \\\\\\n\"","lastModifiedDate":"2019-07-29"},{"lineNumber":21,"author":{"gitId":"-"},"content":"                + \"| |_| | |_| |   \u003c  __/\\n\"","lastModifiedDate":"2019-07-29"},{"lineNumber":22,"author":{"gitId":"-"},"content":"                + \"|____/ \\\\__,_|_|\\\\_\\\\___|\\n\";","lastModifiedDate":"2019-07-29"},{"lineNumber":23,"author":{"gitId":"-"},"content":"        System.out.println(\"Hello from\\n\" + logo);","lastModifiedDate":"2019-07-29"},{"lineNumber":24,"author":{"gitId":"gavienwz"},"content":"        String greet \u003d \"____________________________________________________________\\n\"","lastModifiedDate":"2021-08-20"},{"lineNumber":25,"author":{"gitId":"gavienwz"},"content":"                + \" Hello! I\u0027m Duke\\n\"","lastModifiedDate":"2021-08-20"},{"lineNumber":26,"author":{"gitId":"gavienwz"},"content":"                + \" What can I do for you?\\n\"","lastModifiedDate":"2021-08-20"},{"lineNumber":27,"author":{"gitId":"gavienwz"},"content":"                + \"____________________________________________________________\\n\";","lastModifiedDate":"2021-08-20"},{"lineNumber":28,"author":{"gitId":"gavienwz"},"content":"        System.out.println(greet);","lastModifiedDate":"2021-08-20"},{"lineNumber":29,"author":{"gitId":"gavienwz"},"content":"        String command;","lastModifiedDate":"2021-08-24"},{"lineNumber":30,"author":{"gitId":"gavienwz"},"content":"        Scanner in \u003d new Scanner(System.in);","lastModifiedDate":"2021-08-24"},{"lineNumber":31,"author":{"gitId":"gavienwz"},"content":"        String addition;","lastModifiedDate":"2021-08-24"},{"lineNumber":32,"author":{"gitId":"gavienwz"},"content":"        String bye \u003d \"____________________________________________________________\\n\"","lastModifiedDate":"2021-08-24"},{"lineNumber":33,"author":{"gitId":"gavienwz"},"content":"                +  \" Bye. Hope to see you again soon!\\n\"","lastModifiedDate":"2021-08-24"},{"lineNumber":34,"author":{"gitId":"gavienwz"},"content":"                + \"____________________________________________________________\\n\";","lastModifiedDate":"2021-08-24"},{"lineNumber":35,"author":{"gitId":"gavienwz"},"content":"        String doneMessage;","lastModifiedDate":"2021-08-24"},{"lineNumber":36,"author":{"gitId":"gavienwz"},"content":"        do {","lastModifiedDate":"2021-08-24"},{"lineNumber":37,"author":{"gitId":"gavienwz"},"content":"            command \u003d in.nextLine();","lastModifiedDate":"2021-08-24"},{"lineNumber":38,"author":{"gitId":"gavienwz"},"content":"            if (command.contains(\"done\")) {","lastModifiedDate":"2021-08-24"},{"lineNumber":39,"author":{"gitId":"gavienwz"},"content":"                String[] doneCommand \u003d command.split(\" \");","lastModifiedDate":"2021-08-24"},{"lineNumber":40,"author":{"gitId":"gavienwz"},"content":"                int taskIndex \u003d Integer.parseInt(doneCommand[1]) - 1;","lastModifiedDate":"2021-08-24"},{"lineNumber":41,"author":{"gitId":"gavienwz"},"content":"                tasks[taskIndex].setDone();","lastModifiedDate":"2021-08-24"},{"lineNumber":42,"author":{"gitId":"gavienwz"},"content":"                doneMessage \u003d \"____________________________________________________________\\n\"","lastModifiedDate":"2021-08-24"},{"lineNumber":43,"author":{"gitId":"gavienwz"},"content":"                        + \"Nice! I\u0027ve marked this task as done: \\n\"","lastModifiedDate":"2021-08-24"},{"lineNumber":44,"author":{"gitId":"gavienwz"},"content":"                        + \"[\" + tasks[taskIndex].getStatusIcon() + \"] \" + tasks[taskIndex].description + \"\\n\"","lastModifiedDate":"2021-08-24"},{"lineNumber":45,"author":{"gitId":"gavienwz"},"content":"                        + \"____________________________________________________________\\n\";","lastModifiedDate":"2021-08-24"},{"lineNumber":46,"author":{"gitId":"gavienwz"},"content":"                System.out.println(doneMessage);","lastModifiedDate":"2021-08-24"},{"lineNumber":47,"author":{"gitId":"gavienwz"},"content":"            } else {","lastModifiedDate":"2021-08-24"},{"lineNumber":48,"author":{"gitId":"gavienwz"},"content":"                switch (command) {","lastModifiedDate":"2021-08-24"},{"lineNumber":49,"author":{"gitId":"gavienwz"},"content":"                case \"bye\":","lastModifiedDate":"2021-08-24"},{"lineNumber":50,"author":{"gitId":"gavienwz"},"content":"                    break;","lastModifiedDate":"2021-08-24"},{"lineNumber":51,"author":{"gitId":"gavienwz"},"content":"                case \"list\":","lastModifiedDate":"2021-08-24"},{"lineNumber":52,"author":{"gitId":"gavienwz"},"content":"                    printList();","lastModifiedDate":"2021-08-24"},{"lineNumber":53,"author":{"gitId":"gavienwz"},"content":"                    break;","lastModifiedDate":"2021-08-24"},{"lineNumber":54,"author":{"gitId":"gavienwz"},"content":"                default:","lastModifiedDate":"2021-08-24"},{"lineNumber":55,"author":{"gitId":"gavienwz"},"content":"                    tasks[taskCount] \u003d new Task(command);","lastModifiedDate":"2021-08-24"},{"lineNumber":56,"author":{"gitId":"gavienwz"},"content":"                    taskCount \u003d taskCount + 1;","lastModifiedDate":"2021-08-24"},{"lineNumber":57,"author":{"gitId":"gavienwz"},"content":"                    addition \u003d \"____________________________________________________________\\n\"","lastModifiedDate":"2021-08-24"},{"lineNumber":58,"author":{"gitId":"gavienwz"},"content":"                            + \" added: \" + command + \"\\n\"","lastModifiedDate":"2021-08-24"},{"lineNumber":59,"author":{"gitId":"gavienwz"},"content":"                            + \"____________________________________________________________\\n\";","lastModifiedDate":"2021-08-24"},{"lineNumber":60,"author":{"gitId":"gavienwz"},"content":"                    System.out.println(addition);","lastModifiedDate":"2021-08-24"},{"lineNumber":61,"author":{"gitId":"gavienwz"},"content":"                }","lastModifiedDate":"2021-08-24"},{"lineNumber":62,"author":{"gitId":"gavienwz"},"content":"            }","lastModifiedDate":"2021-08-24"},{"lineNumber":63,"author":{"gitId":"gavienwz"},"content":"        } while (!command.equals(\"bye\"));","lastModifiedDate":"2021-08-24"},{"lineNumber":64,"author":{"gitId":"gavienwz"},"content":"        System.out.println(bye);","lastModifiedDate":"2021-08-24"},{"lineNumber":65,"author":{"gitId":"-"},"content":"    }","lastModifiedDate":"2019-07-29"},{"lineNumber":66,"author":{"gitId":"-"},"content":"}","lastModifiedDate":"2019-07-29"}],"authorContributionMap":{"gavienwz":56,"-":10}},{"path":"src/main/java/Task.java","fileType":"java","lines":[{"lineNumber":1,"author":{"gitId":"gavienwz"},"content":"public class Task {","lastModifiedDate":"2021-08-24"},{"lineNumber":2,"author":{"gitId":"gavienwz"},"content":"    protected String description;","lastModifiedDate":"2021-08-24"},{"lineNumber":3,"author":{"gitId":"gavienwz"},"content":"    protected boolean isDone;","lastModifiedDate":"2021-08-24"},{"lineNumber":4,"author":{"gitId":"gavienwz"},"content":"","lastModifiedDate":"2021-08-24"},{"lineNumber":5,"author":{"gitId":"gavienwz"},"content":"    public Task(String description) {","lastModifiedDate":"2021-08-24"},{"lineNumber":6,"author":{"gitId":"gavienwz"},"content":"        this.description \u003d description;","lastModifiedDate":"2021-08-24"},{"lineNumber":7,"author":{"gitId":"gavienwz"},"content":"        this.isDone \u003d false;","lastModifiedDate":"2021-08-24"},{"lineNumber":8,"author":{"gitId":"gavienwz"},"content":"    }","lastModifiedDate":"2021-08-24"},{"lineNumber":9,"author":{"gitId":"gavienwz"},"content":"","lastModifiedDate":"2021-08-24"},{"lineNumber":10,"author":{"gitId":"gavienwz"},"content":"    public void setDone() {","lastModifiedDate":"2021-08-24"},{"lineNumber":11,"author":{"gitId":"gavienwz"},"content":"        this.isDone \u003d true;","lastModifiedDate":"2021-08-24"},{"lineNumber":12,"author":{"gitId":"gavienwz"},"content":"    }","lastModifiedDate":"2021-08-24"},{"lineNumber":13,"author":{"gitId":"gavienwz"},"content":"","lastModifiedDate":"2021-08-24"},{"lineNumber":14,"author":{"gitId":"gavienwz"},"content":"    public String getStatusIcon() {","lastModifiedDate":"2021-08-24"},{"lineNumber":15,"author":{"gitId":"gavienwz"},"content":"        return (isDone ? \"X\" : \" \"); // mark done task with X","lastModifiedDate":"2021-08-24"},{"lineNumber":16,"author":{"gitId":"gavienwz"},"content":"    }","lastModifiedDate":"2021-08-24"},{"lineNumber":17,"author":{"gitId":"gavienwz"},"content":"}","lastModifiedDate":"2021-08-24"}],"authorContributionMap":{"gavienwz":17}}]
