{"authorDailyContributionsMap":{"Roycius":[{"date":"2021-08-13","commitResults":[{"hash":"bdc982c4308192d26d26119d3258bc56543df34f","messageTitle":"Level-0: Add greeting and goodbye message","messageBody":"","tags":["Level-0"],"fileTypesAndContributionMap":{"java":{"insertions":9,"deletions":6}}}]},{"date":"2021-08-20","commitResults":[{"hash":"5cf8d8b2dbe369a5181526333497f1b70cdca619","messageTitle":"Level-1: add echo functionality","messageBody":"","tags":["Level-1"],"fileTypesAndContributionMap":{"java":{"insertions":19,"deletions":3}}},{"hash":"13b1b9ca16ac686af5f8b9324a5580bb647283b5","messageTitle":"Level-2: add listing feature","messageBody":"","tags":["Level-2"],"fileTypesAndContributionMap":{"java":{"insertions":28,"deletions":10}}},{"hash":"f26db7cc87a96d1e6a12725027e30a9ac1662b28","messageTitle":"Level-3: add \"mark as done\" feature and class \"Task\"","messageBody":"","fileTypesAndContributionMap":{"java":{"insertions":38,"deletions":4}}},{"hash":"be77ec02da3fad203fafea5bd77fdecdd88bffbc","messageTitle":"Level-3: fixed indexing bug and rearranged classes","messageBody":"","fileTypesAndContributionMap":{"java":{"insertions":53,"deletions":54}}}]},{"date":"2021-08-21","commitResults":[{"hash":"747484e9375c63f1a3abe1107ee4ffa5d9b89322","messageTitle":"Level-3: changed listLength to static variable under class Task","messageBody":"","tags":["Level-3"],"fileTypesAndContributionMap":{"java":{"insertions":10,"deletions":6}}},{"hash":"ab304486a5fac04f52f3729645441d2ca0c5b293","messageTitle":"A-CodingStandard: Change some variable names and formatting. Add response for empty task list.","messageBody":"","fileTypesAndContributionMap":{"java":{"insertions":14,"deletions":6}}},{"hash":"9fac0f4aee3d878e813ed0f47a16523822af3f16","messageTitle":"A-CodingStandard: rename listLength to totalTasks.","messageBody":"","tags":["A-CodingStandard"],"fileTypesAndContributionMap":{"java":{"insertions":7,"deletions":7}}}]},{"date":"2021-08-28","commitResults":[{"hash":"cb5ec08f62806a7bebb9e184caf6228cc7fa1900","messageTitle":"Level-4: Add subclasses Todo, Deadline and Event. Optimized code to be more object oriented.","messageBody":"","tags":["Level-4","A-Inheritance"],"fileTypesAndContributionMap":{"java":{"insertions":274,"deletions":50}}},{"hash":"1208a63be1399dd4e3beae8b076ee0eec77627c0","messageTitle":"A-TextUiTesting: add automated UI testing","messageBody":"","tags":["A-TextUiTesting"],"fileTypesAndContributionMap":{"txt":{"insertions":11,"deletions":0},"bat":{"insertions":3,"deletions":2}}},{"hash":"c1f7b4768d029062f63225b80d6f0f9892aca114","messageTitle":"A-CodeQuality: arrange and rename some functions to improve readability. add some documentation.","messageBody":"","tags":["A-CodeQuality"],"fileTypesAndContributionMap":{"java":{"insertions":73,"deletions":35}}}]},{"date":"2021-09-04","commitResults":[{"hash":"6b0126d6387d9557193b75bc504084a0ab3147da","messageTitle":"Level-5: add handling of exceptions. adjusted ui test.","messageBody":"","fileTypesAndContributionMap":{"txt":{"insertions":14,"deletions":6},"java":{"insertions":99,"deletions":29},"bat":{"insertions":2,"deletions":2}}},{"hash":"fb7c0aee0a0b01daf6a244b45918e4b917bb4a7f","messageTitle":"Level-5: Add comments to explain custom exception classes","messageBody":"","fileTypesAndContributionMap":{"java":{"insertions":6,"deletions":0}}},{"hash":"c4f92e7aaecd8f7e7e511e5750d0c03636177463","messageTitle":"A-Packages: split class files into packages","messageBody":"","fileTypesAndContributionMap":{"java":{"insertions":21,"deletions":0},"bat":{"insertions":1,"deletions":1}}},{"hash":"e21770ad38f2ac3bfb2c70fa86ae03c07f9895d6","messageTitle":"A-Packages: fix runtest.bat to cater to the repackaging before. fix typo in a message","messageBody":"","fileTypesAndContributionMap":{"java":{"insertions":1,"deletions":1},"bat":{"insertions":2,"deletions":2}}},{"hash":"1d68684997d973212d94a3f128655fac2b1ed0c2","messageTitle":"A-Packages: removed an extra line from a message","messageBody":"","tags":["A-Packages"],"fileTypesAndContributionMap":{"java":{"insertions":0,"deletions":1}}}]},{"date":"2021-09-10","commitResults":[{"hash":"179ce3018d44926706c420c2cd7bf400050efec7","messageTitle":"A-Collections: change into taskList into ArrayList","messageBody":"","tags":["A-Collections"],"fileTypesAndContributionMap":{"java":{"insertions":11,"deletions":15}}}]},{"date":"2021-09-11","commitResults":[{"hash":"44c5611e599279f450020c86ac2b067f586225b1","messageTitle":"Level-6: add delete function","messageBody":"","fileTypesAndContributionMap":{"txt":{"insertions":9,"deletions":2},"java":{"insertions":43,"deletions":1}}},{"hash":"1f2cc075e19d25e85dade4544e93398d042da6f7","messageTitle":"Level-7: add hard disk saving and loading functionality","messageBody":"","fileTypesAndContributionMap":{"java":{"insertions":136,"deletions":8},"bat":{"insertions":1,"deletions":0}}},{"hash":"a8d0e7ff552f65c464a45c40e0e1e09593c8b3b6","messageTitle":"Revert \"Level-7: add hard disk saving and loading functionality\"","messageBody":"This reverts commit 1f2cc075e19d25e85dade4544e93398d042da6f7.\n","fileTypesAndContributionMap":{"java":{"insertions":8,"deletions":136},"bat":{"insertions":0,"deletions":1}}},{"hash":"8b765e83774690babca968e2a41ca03433e1d0f6","messageTitle":"Revert \"Level-6: add delete function\"","messageBody":"This reverts commit 44c5611e599279f450020c86ac2b067f586225b1.\n","fileTypesAndContributionMap":{"txt":{"insertions":2,"deletions":9},"java":{"insertions":1,"deletions":43}}},{"hash":"03bd7bf8656f017746c8d3f027f63882b92219b7","messageTitle":"Level-6: add delete function and change ui test","messageBody":"","fileTypesAndContributionMap":{"txt":{"insertions":10,"deletions":4},"java":{"insertions":43,"deletions":1}}},{"hash":"5280b09915eb53589d9bd2c6b7d68bafeed588e9","messageTitle":"Level-7: add hard disk saving and loading functionality","messageBody":"","fileTypesAndContributionMap":{"java":{"insertions":132,"deletions":11},"bat":{"insertions":1,"deletions":0}}}]},{"date":"2021-09-17","commitResults":[{"hash":"b20e05a9ec3ab67530b43e1c39b5a4a4c7393d49","messageTitle":"A-MoreOOP: design overhaul to make code more OOP oriented","messageBody":"","fileTypesAndContributionMap":{"java":{"insertions":547,"deletions":408}}},{"hash":"a9b2385dbfb06f49cc38b0b943b472e2dce1c937","messageTitle":"Fixed some indentation and comments","messageBody":"","tags":["A-MoreOOP"],"fileTypesAndContributionMap":{"java":{"insertions":16,"deletions":11}}}]},{"date":"2021-09-19","commitResults":[{"hash":"1d6d8e3ca8190f4bae1d0d140b0de9f6aa3d8d14","messageTitle":"Level-8: add DateTime feature to keep track of upcoming deadlines and events","messageBody":"","fileTypesAndContributionMap":{"java":{"insertions":191,"deletions":21}}},{"hash":"f327962868f2e29868a285c030164b4556f12239","messageTitle":"Level-8: updated prompt for invalid command","messageBody":"","fileTypesAndContributionMap":{"java":{"insertions":1,"deletions":1}}},{"hash":"cebc4219bc10ab367442efa1045391afbc760526","messageTitle":"Level-9: add \"find\" function to search for tasks containing a keyword","messageBody":"","fileTypesAndContributionMap":{"java":{"insertions":75,"deletions":1}}},{"hash":"b3e26fea3140d99a3eebcd81a5c39926af2886b1","messageTitle":"Level-9: add documentation and comments for some search methods","messageBody":"","fileTypesAndContributionMap":{"java":{"insertions":16,"deletions":1}}}]},{"date":"2021-09-20","commitResults":[{"hash":"c5e622e759ea4f93e0d638657480245d0954e2f9","messageTitle":"A-JavaDoc: add JavaDoc comments to methods and classes and improved on existing ones","messageBody":"","fileTypesAndContributionMap":{"java":{"insertions":125,"deletions":35}}}]},{"date":"2021-09-21","commitResults":[{"hash":"65720fb718a4cfe84803e9aad3169f8a8dc0af55","messageTitle":"A-UserGuide: Create user guide","messageBody":"","fileTypesAndContributionMap":{"md":{"insertions":167,"deletions":24}}},{"hash":"b29d98aa019952e5557c31374aed96ab5e4cbb21","messageTitle":"A-UserGuide: Attempt 1 in fixing header issue in the user guide","messageBody":"","fileTypesAndContributionMap":{"md":{"insertions":13,"deletions":13}}},{"hash":"52f1951b2a95c7b81b374f1d9d9aa74d647d6004","messageTitle":"A-UserGuide: Moved user guide to the correct location","messageBody":"","fileTypesAndContributionMap":{"md":{"insertions":176,"deletions":181}}},{"hash":"eee46d0830ed3e1760cb9fac07d2d5ec8d5c6684","messageTitle":"A-UserGuide: Attempt to fix github page rendering","messageBody":"","fileTypesAndContributionMap":{"md":{"insertions":0,"deletions":1}}},{"hash":"8f2e268ce4a8be7833f1ee3758a6b3a08b7c6e17","messageTitle":"A-UserGuide: Attempt 2 to fix github page render","messageBody":"","fileTypesAndContributionMap":{"md":{"insertions":2,"deletions":0}}},{"hash":"4e0952e4a247ba8375aa7f220d3557ff833e308d","messageTitle":"A-UserGuide: Refine user guide","messageBody":"","fileTypesAndContributionMap":{"md":{"insertions":18,"deletions":18}}},{"hash":"fc348d33db2a773d70ddf6b6f7bbdda7f1e2ce78","messageTitle":"A-UserGuide: Add feature summary to user guide.","messageBody":"","tags":["A-UserGuide","A-Release"],"fileTypesAndContributionMap":{"md":{"insertions":25,"deletions":1}}}]}]},"authorFileTypeContributionMap":{"Roycius":{"java":1180,"md":177,"fxml":0,"sh":0,"bat":4,"gradle":0,"txt":25}},"authorContributionVariance":{"Roycius":8341.746},"authorDisplayNameMap":{"Roycius":"CS2113T-W11-3 ROYC..NWEI"}}
