[{"path":"src/main/java/Deadline.java","fileType":"java","lines":[{"lineNumber":1,"author":{"gitId":"SvethaMahadevan"},"content":"public class Deadline extends Task {","lastModifiedDate":"2021-08-31"},{"lineNumber":2,"author":{"gitId":"SvethaMahadevan"},"content":"    protected String by;","lastModifiedDate":"2021-08-31"},{"lineNumber":3,"author":{"gitId":"SvethaMahadevan"},"content":"","lastModifiedDate":"2021-08-31"},{"lineNumber":4,"author":{"gitId":"SvethaMahadevan"},"content":"    public Deadline(String description, String by) {","lastModifiedDate":"2021-08-31"},{"lineNumber":5,"author":{"gitId":"SvethaMahadevan"},"content":"        super(description);","lastModifiedDate":"2021-08-31"},{"lineNumber":6,"author":{"gitId":"SvethaMahadevan"},"content":"        this.by \u003d by;","lastModifiedDate":"2021-08-31"},{"lineNumber":7,"author":{"gitId":"SvethaMahadevan"},"content":"    }","lastModifiedDate":"2021-08-31"},{"lineNumber":8,"author":{"gitId":"SvethaMahadevan"},"content":"","lastModifiedDate":"2021-08-31"},{"lineNumber":9,"author":{"gitId":"SvethaMahadevan"},"content":"    public String getStatusIcon() {","lastModifiedDate":"2021-08-31"},{"lineNumber":10,"author":{"gitId":"SvethaMahadevan"},"content":"        return \"[D]\" + (isDone ? \"[X]\" : \"[ ]\"); //return tick or X symbols","lastModifiedDate":"2021-08-31"},{"lineNumber":11,"author":{"gitId":"SvethaMahadevan"},"content":"    }","lastModifiedDate":"2021-08-31"},{"lineNumber":12,"author":{"gitId":"SvethaMahadevan"},"content":"","lastModifiedDate":"2021-08-31"},{"lineNumber":13,"author":{"gitId":"SvethaMahadevan"},"content":"    @Override","lastModifiedDate":"2021-08-31"},{"lineNumber":14,"author":{"gitId":"SvethaMahadevan"},"content":"    public String toString() {","lastModifiedDate":"2021-08-31"},{"lineNumber":15,"author":{"gitId":"SvethaMahadevan"},"content":"        return this.getStatusIcon() + description + \"(by:\" + by + \")\";","lastModifiedDate":"2021-08-31"},{"lineNumber":16,"author":{"gitId":"SvethaMahadevan"},"content":"    }","lastModifiedDate":"2021-08-31"},{"lineNumber":17,"author":{"gitId":"SvethaMahadevan"},"content":"","lastModifiedDate":"2021-08-31"},{"lineNumber":18,"author":{"gitId":"SvethaMahadevan"},"content":"    public void markAsDone() {","lastModifiedDate":"2021-08-31"},{"lineNumber":19,"author":{"gitId":"SvethaMahadevan"},"content":"        this.isDone \u003d true;","lastModifiedDate":"2021-08-31"},{"lineNumber":20,"author":{"gitId":"SvethaMahadevan"},"content":"    }","lastModifiedDate":"2021-08-31"},{"lineNumber":21,"author":{"gitId":"SvethaMahadevan"},"content":"}","lastModifiedDate":"2021-08-31"}],"authorContributionMap":{"SvethaMahadevan":21}},{"path":"src/main/java/Duke.java","fileType":"java","lines":[{"lineNumber":1,"author":{"gitId":"SvethaMahadevan"},"content":"import java.util.*;","lastModifiedDate":"2021-08-23"},{"lineNumber":2,"author":{"gitId":"SvethaMahadevan"},"content":"","lastModifiedDate":"2021-08-26"},{"lineNumber":3,"author":{"gitId":"-"},"content":"public class Duke {","lastModifiedDate":"2019-07-29"},{"lineNumber":4,"author":{"gitId":"SvethaMahadevan"},"content":"    private static Task[] taskList;","lastModifiedDate":"2021-08-24"},{"lineNumber":5,"author":{"gitId":"SvethaMahadevan"},"content":"    private static int taskCount;","lastModifiedDate":"2021-08-31"},{"lineNumber":6,"author":{"gitId":"SvethaMahadevan"},"content":"","lastModifiedDate":"2021-08-23"},{"lineNumber":7,"author":{"gitId":"SvethaMahadevan"},"content":"    public static void addTask(String task) {","lastModifiedDate":"2021-08-23"},{"lineNumber":8,"author":{"gitId":"SvethaMahadevan"},"content":"        if (task.startsWith(\"todo\")) {","lastModifiedDate":"2021-08-31"},{"lineNumber":9,"author":{"gitId":"SvethaMahadevan"},"content":"            taskList[taskCount] \u003d new Todo(task.substring(\"task\".length()));","lastModifiedDate":"2021-08-31"},{"lineNumber":10,"author":{"gitId":"SvethaMahadevan"},"content":"        } else if (task.startsWith(\"deadline\")) {","lastModifiedDate":"2021-08-31"},{"lineNumber":11,"author":{"gitId":"SvethaMahadevan"},"content":"            taskList[taskCount] \u003d new Deadline(task.substring(\"deadline\".length(), task.indexOf(\"/by\")), task.substring(task.indexOf(\"/by\") + \"/by\".length()));","lastModifiedDate":"2021-08-31"},{"lineNumber":12,"author":{"gitId":"SvethaMahadevan"},"content":"        } else if (task.startsWith(\"event\")) {","lastModifiedDate":"2021-08-31"},{"lineNumber":13,"author":{"gitId":"SvethaMahadevan"},"content":"            taskList[taskCount] \u003d new Event(task.substring(\"event\".length(), task.indexOf(\"/at\")), task.substring(task.indexOf(\"/at\") + \"/at\".length()));","lastModifiedDate":"2021-08-31"},{"lineNumber":14,"author":{"gitId":"SvethaMahadevan"},"content":"        }","lastModifiedDate":"2021-08-31"},{"lineNumber":15,"author":{"gitId":"SvethaMahadevan"},"content":"        printWithLines(\"Got it. I\u0027ve added this task:\\n\" + taskList[taskCount].toString() + \"\\nNow you have \" + (taskCount + 1) + \" tasks in the list\");","lastModifiedDate":"2021-08-31"},{"lineNumber":16,"author":{"gitId":"SvethaMahadevan"},"content":"        taskCount++;","lastModifiedDate":"2021-08-31"},{"lineNumber":17,"author":{"gitId":"SvethaMahadevan"},"content":"    }","lastModifiedDate":"2021-08-23"},{"lineNumber":18,"author":{"gitId":"SvethaMahadevan"},"content":"","lastModifiedDate":"2021-08-23"},{"lineNumber":19,"author":{"gitId":"SvethaMahadevan"},"content":"    public static void listTasks() {","lastModifiedDate":"2021-08-31"},{"lineNumber":20,"author":{"gitId":"SvethaMahadevan"},"content":"        String tasksAsList \u003d \"\";","lastModifiedDate":"2021-08-24"},{"lineNumber":21,"author":{"gitId":"SvethaMahadevan"},"content":"        for (int i \u003d 0; i \u003c taskCount; i++) {","lastModifiedDate":"2021-08-31"},{"lineNumber":22,"author":{"gitId":"SvethaMahadevan"},"content":"            tasksAsList \u003d tasksAsList.concat((i + 1) + \".\" +","lastModifiedDate":"2021-08-31"},{"lineNumber":23,"author":{"gitId":"SvethaMahadevan"},"content":"                    taskList[i].toString() + \"\\n\");","lastModifiedDate":"2021-08-31"},{"lineNumber":24,"author":{"gitId":"SvethaMahadevan"},"content":"        }","lastModifiedDate":"2021-08-23"},{"lineNumber":25,"author":{"gitId":"SvethaMahadevan"},"content":"        tasksAsList \u003d tasksAsList.substring(0, tasksAsList.length() - 1);","lastModifiedDate":"2021-08-24"},{"lineNumber":26,"author":{"gitId":"SvethaMahadevan"},"content":"        printWithLines(\"Here are the tasks in your list:\\n\" + tasksAsList);","lastModifiedDate":"2021-08-31"},{"lineNumber":27,"author":{"gitId":"SvethaMahadevan"},"content":"    }","lastModifiedDate":"2021-08-23"},{"lineNumber":28,"author":{"gitId":"SvethaMahadevan"},"content":"","lastModifiedDate":"2021-08-24"},{"lineNumber":29,"author":{"gitId":"SvethaMahadevan"},"content":"    public static void markTaskAsDone(String task) {","lastModifiedDate":"2021-08-31"},{"lineNumber":30,"author":{"gitId":"SvethaMahadevan"},"content":"        int taskIndex \u003d Integer.parseInt(task.replace(\"done \", \"\")) -  1;","lastModifiedDate":"2021-08-24"},{"lineNumber":31,"author":{"gitId":"SvethaMahadevan"},"content":"        if (taskIndex \u003e taskCount - 1) {","lastModifiedDate":"2021-08-31"},{"lineNumber":32,"author":{"gitId":"SvethaMahadevan"},"content":"            printWithLines(\" The task \" + (taskIndex + 1) + \" doesn\u0027t exist.\\nMake sure a valid task number is entered.\");","lastModifiedDate":"2021-08-24"},{"lineNumber":33,"author":{"gitId":"SvethaMahadevan"},"content":"            return;","lastModifiedDate":"2021-08-24"},{"lineNumber":34,"author":{"gitId":"SvethaMahadevan"},"content":"        }","lastModifiedDate":"2021-08-24"},{"lineNumber":35,"author":{"gitId":"SvethaMahadevan"},"content":"        Task current \u003d taskList[taskIndex];","lastModifiedDate":"2021-08-24"},{"lineNumber":36,"author":{"gitId":"SvethaMahadevan"},"content":"        current.markAsDone();","lastModifiedDate":"2021-08-24"},{"lineNumber":37,"author":{"gitId":"SvethaMahadevan"},"content":"        printWithLines(\"Nice! I\u0027ve marked this task as done:\\n\" + current.toString());","lastModifiedDate":"2021-08-31"},{"lineNumber":38,"author":{"gitId":"SvethaMahadevan"},"content":"    }","lastModifiedDate":"2021-08-24"},{"lineNumber":39,"author":{"gitId":"SvethaMahadevan"},"content":"","lastModifiedDate":"2021-08-24"},{"lineNumber":40,"author":{"gitId":"SvethaMahadevan"},"content":"    public static void printWithLines(String output) {","lastModifiedDate":"2021-08-24"},{"lineNumber":41,"author":{"gitId":"SvethaMahadevan"},"content":"        String horizontalLine \u003d \"____________________________________________________________\";","lastModifiedDate":"2021-08-23"},{"lineNumber":42,"author":{"gitId":"SvethaMahadevan"},"content":"        System.out.println(horizontalLine);","lastModifiedDate":"2021-08-23"},{"lineNumber":43,"author":{"gitId":"SvethaMahadevan"},"content":"        System.out.println(output);","lastModifiedDate":"2021-08-23"},{"lineNumber":44,"author":{"gitId":"SvethaMahadevan"},"content":"        System.out.println(horizontalLine);","lastModifiedDate":"2021-08-23"},{"lineNumber":45,"author":{"gitId":"SvethaMahadevan"},"content":"    }","lastModifiedDate":"2021-08-23"},{"lineNumber":46,"author":{"gitId":"SvethaMahadevan"},"content":"","lastModifiedDate":"2021-08-23"},{"lineNumber":47,"author":{"gitId":"-"},"content":"    public static void main(String[] args) {","lastModifiedDate":"2021-08-23"},{"lineNumber":48,"author":{"gitId":"SvethaMahadevan"},"content":"        taskList \u003d new Task[100];","lastModifiedDate":"2021-08-24"},{"lineNumber":49,"author":{"gitId":"SvethaMahadevan"},"content":"        taskCount \u003d 0;","lastModifiedDate":"2021-08-31"},{"lineNumber":50,"author":{"gitId":"SvethaMahadevan"},"content":"        String userInput;","lastModifiedDate":"2021-08-23"},{"lineNumber":51,"author":{"gitId":"-"},"content":"        String logo \u003d \" ____        _        \\n\"","lastModifiedDate":"2019-07-29"},{"lineNumber":52,"author":{"gitId":"-"},"content":"                + \"|  _ \\\\ _   _| | _____ \\n\"","lastModifiedDate":"2019-07-29"},{"lineNumber":53,"author":{"gitId":"-"},"content":"                + \"| | | | | | | |/ / _ \\\\\\n\"","lastModifiedDate":"2019-07-29"},{"lineNumber":54,"author":{"gitId":"-"},"content":"                + \"| |_| | |_| |   \u003c  __/\\n\"","lastModifiedDate":"2019-07-29"},{"lineNumber":55,"author":{"gitId":"-"},"content":"                + \"|____/ \\\\__,_|_|\\\\_\\\\___|\\n\";","lastModifiedDate":"2019-07-29"},{"lineNumber":56,"author":{"gitId":"-"},"content":"        System.out.println(\"Hello from\\n\" + logo);","lastModifiedDate":"2019-07-29"},{"lineNumber":57,"author":{"gitId":"SvethaMahadevan"},"content":"        printWithLines(\"Hello! I\u0027m Duke\\n\" + \"What can I do for you?\");","lastModifiedDate":"2021-08-24"},{"lineNumber":58,"author":{"gitId":"SvethaMahadevan"},"content":"        Scanner in \u003d new Scanner(System.in);","lastModifiedDate":"2021-08-23"},{"lineNumber":59,"author":{"gitId":"SvethaMahadevan"},"content":"        userInput \u003d in.nextLine();","lastModifiedDate":"2021-08-23"},{"lineNumber":60,"author":{"gitId":"SvethaMahadevan"},"content":"        while (!userInput.equals(\"bye\"))","lastModifiedDate":"2021-08-24"},{"lineNumber":61,"author":{"gitId":"SvethaMahadevan"},"content":"        {","lastModifiedDate":"2021-08-23"},{"lineNumber":62,"author":{"gitId":"SvethaMahadevan"},"content":"            if (userInput.equals(\"list\")) {","lastModifiedDate":"2021-08-24"},{"lineNumber":63,"author":{"gitId":"SvethaMahadevan"},"content":"                listTasks();","lastModifiedDate":"2021-08-31"},{"lineNumber":64,"author":{"gitId":"SvethaMahadevan"},"content":"            } else if (userInput.startsWith(\"done\")) {","lastModifiedDate":"2021-08-31"},{"lineNumber":65,"author":{"gitId":"SvethaMahadevan"},"content":"                markTaskAsDone(userInput);","lastModifiedDate":"2021-08-31"},{"lineNumber":66,"author":{"gitId":"SvethaMahadevan"},"content":"            } else {","lastModifiedDate":"2021-08-31"},{"lineNumber":67,"author":{"gitId":"SvethaMahadevan"},"content":"                addTask(userInput);","lastModifiedDate":"2021-08-23"},{"lineNumber":68,"author":{"gitId":"SvethaMahadevan"},"content":"            }","lastModifiedDate":"2021-08-26"},{"lineNumber":69,"author":{"gitId":"SvethaMahadevan"},"content":"            userInput \u003d in.nextLine();","lastModifiedDate":"2021-08-23"},{"lineNumber":70,"author":{"gitId":"SvethaMahadevan"},"content":"        }","lastModifiedDate":"2021-08-23"},{"lineNumber":71,"author":{"gitId":"SvethaMahadevan"},"content":"        printWithLines(\"Bye. Hope to see you again soon!\");","lastModifiedDate":"2021-08-24"},{"lineNumber":72,"author":{"gitId":"-"},"content":"    }","lastModifiedDate":"2019-07-29"},{"lineNumber":73,"author":{"gitId":"-"},"content":"}","lastModifiedDate":"2019-07-29"}],"authorContributionMap":{"SvethaMahadevan":63,"-":10}},{"path":"src/main/java/Event.java","fileType":"java","lines":[{"lineNumber":1,"author":{"gitId":"SvethaMahadevan"},"content":"public class Event extends Task {","lastModifiedDate":"2021-08-31"},{"lineNumber":2,"author":{"gitId":"SvethaMahadevan"},"content":"    protected String at;","lastModifiedDate":"2021-08-31"},{"lineNumber":3,"author":{"gitId":"SvethaMahadevan"},"content":"","lastModifiedDate":"2021-08-31"},{"lineNumber":4,"author":{"gitId":"SvethaMahadevan"},"content":"    public Event(String description, String at) {","lastModifiedDate":"2021-08-31"},{"lineNumber":5,"author":{"gitId":"SvethaMahadevan"},"content":"        super(description);","lastModifiedDate":"2021-08-31"},{"lineNumber":6,"author":{"gitId":"SvethaMahadevan"},"content":"        this.at \u003d at;","lastModifiedDate":"2021-08-31"},{"lineNumber":7,"author":{"gitId":"SvethaMahadevan"},"content":"    }","lastModifiedDate":"2021-08-31"},{"lineNumber":8,"author":{"gitId":"SvethaMahadevan"},"content":"","lastModifiedDate":"2021-08-31"},{"lineNumber":9,"author":{"gitId":"SvethaMahadevan"},"content":"    public String getStatusIcon() {","lastModifiedDate":"2021-08-31"},{"lineNumber":10,"author":{"gitId":"SvethaMahadevan"},"content":"        return \"[E]\" + (isDone ? \"[X]\" : \"[ ]\"); //return tick or X symbols","lastModifiedDate":"2021-08-31"},{"lineNumber":11,"author":{"gitId":"SvethaMahadevan"},"content":"    }","lastModifiedDate":"2021-08-31"},{"lineNumber":12,"author":{"gitId":"SvethaMahadevan"},"content":"","lastModifiedDate":"2021-08-31"},{"lineNumber":13,"author":{"gitId":"SvethaMahadevan"},"content":"    @Override","lastModifiedDate":"2021-08-31"},{"lineNumber":14,"author":{"gitId":"SvethaMahadevan"},"content":"    public String toString() {","lastModifiedDate":"2021-08-31"},{"lineNumber":15,"author":{"gitId":"SvethaMahadevan"},"content":"        return this.getStatusIcon() + description + \"(at:\" + at + \")\";","lastModifiedDate":"2021-08-31"},{"lineNumber":16,"author":{"gitId":"SvethaMahadevan"},"content":"    }","lastModifiedDate":"2021-08-31"},{"lineNumber":17,"author":{"gitId":"SvethaMahadevan"},"content":"","lastModifiedDate":"2021-08-31"},{"lineNumber":18,"author":{"gitId":"SvethaMahadevan"},"content":"    public void markAsDone() {","lastModifiedDate":"2021-08-31"},{"lineNumber":19,"author":{"gitId":"SvethaMahadevan"},"content":"        this.isDone \u003d true;","lastModifiedDate":"2021-08-31"},{"lineNumber":20,"author":{"gitId":"SvethaMahadevan"},"content":"    }","lastModifiedDate":"2021-08-31"},{"lineNumber":21,"author":{"gitId":"SvethaMahadevan"},"content":"}","lastModifiedDate":"2021-08-31"}],"authorContributionMap":{"SvethaMahadevan":21}},{"path":"src/main/java/Task.java","fileType":"java","lines":[{"lineNumber":1,"author":{"gitId":"SvethaMahadevan"},"content":"public class Task {","lastModifiedDate":"2021-08-24"},{"lineNumber":2,"author":{"gitId":"SvethaMahadevan"},"content":"    protected String description;","lastModifiedDate":"2021-08-24"},{"lineNumber":3,"author":{"gitId":"SvethaMahadevan"},"content":"    protected boolean isDone;","lastModifiedDate":"2021-08-24"},{"lineNumber":4,"author":{"gitId":"SvethaMahadevan"},"content":"","lastModifiedDate":"2021-08-24"},{"lineNumber":5,"author":{"gitId":"SvethaMahadevan"},"content":"    public Task(String description) {","lastModifiedDate":"2021-08-24"},{"lineNumber":6,"author":{"gitId":"SvethaMahadevan"},"content":"        this.description \u003d description;","lastModifiedDate":"2021-08-24"},{"lineNumber":7,"author":{"gitId":"SvethaMahadevan"},"content":"        this.isDone \u003d false;","lastModifiedDate":"2021-08-24"},{"lineNumber":8,"author":{"gitId":"SvethaMahadevan"},"content":"    }","lastModifiedDate":"2021-08-24"},{"lineNumber":9,"author":{"gitId":"SvethaMahadevan"},"content":"","lastModifiedDate":"2021-08-24"},{"lineNumber":10,"author":{"gitId":"SvethaMahadevan"},"content":"    public String getStatusIcon() {","lastModifiedDate":"2021-08-24"},{"lineNumber":11,"author":{"gitId":"SvethaMahadevan"},"content":"        return (isDone ? \"X\" : \" \"); // mark done task with X","lastModifiedDate":"2021-08-24"},{"lineNumber":12,"author":{"gitId":"SvethaMahadevan"},"content":"    }","lastModifiedDate":"2021-08-24"},{"lineNumber":13,"author":{"gitId":"SvethaMahadevan"},"content":"","lastModifiedDate":"2021-08-24"},{"lineNumber":14,"author":{"gitId":"SvethaMahadevan"},"content":"    public void markAsDone() {","lastModifiedDate":"2021-08-24"},{"lineNumber":15,"author":{"gitId":"SvethaMahadevan"},"content":"        this.isDone \u003d true;","lastModifiedDate":"2021-08-24"},{"lineNumber":16,"author":{"gitId":"SvethaMahadevan"},"content":"    }","lastModifiedDate":"2021-08-24"},{"lineNumber":17,"author":{"gitId":"SvethaMahadevan"},"content":"}","lastModifiedDate":"2021-08-24"}],"authorContributionMap":{"SvethaMahadevan":17}},{"path":"src/main/java/Todo.java","fileType":"java","lines":[{"lineNumber":1,"author":{"gitId":"SvethaMahadevan"},"content":"public class Todo extends Task {","lastModifiedDate":"2021-08-31"},{"lineNumber":2,"author":{"gitId":"SvethaMahadevan"},"content":"","lastModifiedDate":"2021-08-31"},{"lineNumber":3,"author":{"gitId":"SvethaMahadevan"},"content":"    public Todo(String description) {","lastModifiedDate":"2021-08-31"},{"lineNumber":4,"author":{"gitId":"SvethaMahadevan"},"content":"        super(description);","lastModifiedDate":"2021-08-31"},{"lineNumber":5,"author":{"gitId":"SvethaMahadevan"},"content":"    }","lastModifiedDate":"2021-08-31"},{"lineNumber":6,"author":{"gitId":"SvethaMahadevan"},"content":"","lastModifiedDate":"2021-08-31"},{"lineNumber":7,"author":{"gitId":"SvethaMahadevan"},"content":"    public String getStatusIcon() {","lastModifiedDate":"2021-08-31"},{"lineNumber":8,"author":{"gitId":"SvethaMahadevan"},"content":"        return \"[T]\" + (isDone ? \"[X]\" : \"[ ]\"); //return tick or X symbols","lastModifiedDate":"2021-08-31"},{"lineNumber":9,"author":{"gitId":"SvethaMahadevan"},"content":"    }","lastModifiedDate":"2021-08-31"},{"lineNumber":10,"author":{"gitId":"SvethaMahadevan"},"content":"","lastModifiedDate":"2021-08-31"},{"lineNumber":11,"author":{"gitId":"SvethaMahadevan"},"content":"    @Override","lastModifiedDate":"2021-08-31"},{"lineNumber":12,"author":{"gitId":"SvethaMahadevan"},"content":"    public String toString() {","lastModifiedDate":"2021-08-31"},{"lineNumber":13,"author":{"gitId":"SvethaMahadevan"},"content":"        return this.getStatusIcon() + description;","lastModifiedDate":"2021-08-31"},{"lineNumber":14,"author":{"gitId":"SvethaMahadevan"},"content":"    }","lastModifiedDate":"2021-08-31"},{"lineNumber":15,"author":{"gitId":"SvethaMahadevan"},"content":"","lastModifiedDate":"2021-08-31"},{"lineNumber":16,"author":{"gitId":"SvethaMahadevan"},"content":"    public void markAsDone() {","lastModifiedDate":"2021-08-31"},{"lineNumber":17,"author":{"gitId":"SvethaMahadevan"},"content":"        this.isDone \u003d true;","lastModifiedDate":"2021-08-31"},{"lineNumber":18,"author":{"gitId":"SvethaMahadevan"},"content":"    }","lastModifiedDate":"2021-08-31"},{"lineNumber":19,"author":{"gitId":"SvethaMahadevan"},"content":"}","lastModifiedDate":"2021-08-31"}],"authorContributionMap":{"SvethaMahadevan":19}},{"path":"text-ui-test/input.txt","fileType":"txt","lines":[{"lineNumber":1,"author":{"gitId":"SvethaMahadevan"},"content":"todo read book","lastModifiedDate":"2021-08-31"}],"authorContributionMap":{"SvethaMahadevan":1}}]
