{"authorDailyContributionsMap":{"bernardboey":[{"date":"2021-08-19","commitResults":[{"hash":"5d002c5c4112b72e5af3b86855303182cdbef022","messageTitle":"Add greeting and exit messages","messageBody":"","tags":["Level-0"],"fileTypesAndContributionMap":{"java":{"insertions":18,"deletions":6}}}]},{"date":"2021-08-24","commitResults":[{"hash":"cbcc093fcfedba962dd24fa9f857a9db7dfaff4b","messageTitle":"Add support for echoing commands and indentation","messageBody":"","tags":["Level-1"],"fileTypesAndContributionMap":{"java":{"insertions":34,"deletions":8}}},{"hash":"2b6b1d935f5d24b57ab5bd0db0d65141d780f9e4","messageTitle":"Add support for storing and displaying a list of items","messageBody":"","tags":["Level-2"],"fileTypesAndContributionMap":{"java":{"insertions":36,"deletions":13}}},{"hash":"0868217f8a8b44f344d3fe68b8e3182c1bc9e48e","messageTitle":"Add Task class and integrate with Duke","messageBody":"","tags":["A-Classes"],"fileTypesAndContributionMap":{"java":{"insertions":35,"deletions":14}}},{"hash":"65f6d273ef7662db4402eeaaef90fc279fd0ab39","messageTitle":"Add support for marking tasks as done","messageBody":"","tags":["Level-3"],"fileTypesAndContributionMap":{"java":{"insertions":24,"deletions":9}}},{"hash":"87524cf61632018d653c9dd9523063691a9e4521","messageTitle":"Add Javadoc comments and conform to coding standard","messageBody":"","tags":["A-CodingStandard"],"fileTypesAndContributionMap":{"java":{"insertions":52,"deletions":15}}}]},{"date":"2021-08-26","commitResults":[{"hash":"c45e6acf6531fbc841bf30b493c09e5bd6e7cee8","messageTitle":"Implement Todo, Deadline, and Event classes","messageBody":"","tags":["A-Inheritance"],"fileTypesAndContributionMap":{"java":{"insertions":44,"deletions":0}}}]},{"date":"2021-09-01","commitResults":[{"hash":"b8c9379cc47e59d92ff5a15d1ddbf86f70ec3669","messageTitle":"Add support for tracking ToDos, Deadlines, and Events","messageBody":"","tags":["Level-4"],"fileTypesAndContributionMap":{"java":{"insertions":42,"deletions":9}}},{"hash":"2d338464f3121d672dd58c97de1c21356fa9a86c","messageTitle":"Add text UI testing","messageBody":"","tags":["A-TextUiTesting"],"fileTypesAndContributionMap":{"txt":{"insertions":22,"deletions":0}}},{"hash":"dafb619cfb4c43afe1717eb142b0547645970b20","messageTitle":"Add Javadoc comments and improve code quality","messageBody":"","tags":["A-CodeQuality"],"fileTypesAndContributionMap":{"java":{"insertions":55,"deletions":5}}}]},{"date":"2021-09-04","commitResults":[{"hash":"7d34da8239985730c1c68957b4420711b2c0a02f","messageTitle":"Organize classes into packages","messageBody":"","tags":["A-Packages"],"fileTypesAndContributionMap":{"java":{"insertions":15,"deletions":0}}},{"hash":"17a84a67405b67acca1229e589ab1f89b750e816","messageTitle":"Handle incorrect input (no description for todo)","messageBody":"","fileTypesAndContributionMap":{"java":{"insertions":4,"deletions":0}}},{"hash":"2f12a431528260c03634ec49d58cea066f937b73","messageTitle":"Handle incorrect input (unrecognised command)","messageBody":"","fileTypesAndContributionMap":{"java":{"insertions":5,"deletions":0}}}]},{"date":"2021-09-05","commitResults":[{"hash":"6c1d8607344f533f9fd9225e8a7b329c9c9950c5","messageTitle":"Define and use DukeException to handle errors specific to Duke","messageBody":"","tags":["A-Exceptions"],"fileTypesAndContributionMap":{"java":{"insertions":39,"deletions":29}}},{"hash":"2a46fb61cab7bc7f61a0efd5cf901004b51b97e9","messageTitle":"Update text ui test","messageBody":"","fileTypesAndContributionMap":{"txt":{"insertions":2,"deletions":0},"bat":{"insertions":2,"deletions":2}}}]},{"date":"2021-09-08","commitResults":[{"hash":"04a6155414c064e9eece5df01ba0bcaef350617b","messageTitle":"Improve code quality","messageBody":"","fileTypesAndContributionMap":{"java":{"insertions":128,"deletions":93}}}]},{"date":"2021-09-13","commitResults":[{"hash":"83ee0cbd682bf407eab736eb763911d0d3e939c7","messageTitle":"Use ArrayList instead of Array to store tasks","messageBody":"","tags":["A-Collections"],"fileTypesAndContributionMap":{"java":{"insertions":8,"deletions":12}}},{"hash":"013c9f031da6be2ec0d45d7973713edf206f7362","messageTitle":"Add support for deleting tasks","messageBody":"","fileTypesAndContributionMap":{"txt":{"insertions":2,"deletions":0},"java":{"insertions":12,"deletions":0}}},{"hash":"86920a1a7ac02043222cb81c76dccc1839b13f9d","messageTitle":"Improve code quality","messageBody":"","fileTypesAndContributionMap":{"java":{"insertions":9,"deletions":7}}}]},{"date":"2021-09-15","commitResults":[{"hash":"b19dc9c4e20255d78f70795dea36d863329bbba5","messageTitle":"Add support for saving tasks in hard disk","messageBody":"","fileTypesAndContributionMap":{"java":{"insertions":163,"deletions":17}}},{"hash":"d46adcfdc5a532f0363fb8c0be4783473a6b8a21","messageTitle":"Update tests to account for saving of tasks in hard disk","messageBody":"","fileTypesAndContributionMap":{"bat":{"insertions":3,"deletions":0},"sh":{"insertions":7,"deletions":0}}},{"hash":"cf3ae2ec00f6372f0675bf6430447a864ae16dac","messageTitle":"Improve code quality","messageBody":"","fileTypesAndContributionMap":{"java":{"insertions":23,"deletions":17}}},{"hash":"9dcf3019736d3aa0ec1bddf7ac6520ba1b6cc9ef","messageTitle":"Save data when tasks are deleted","messageBody":"","tags":["Level-7"],"fileTypesAndContributionMap":{"java":{"insertions":1,"deletions":0}}},{"hash":"7c67a6b4af152ada14697af53d21c811960a9112","messageTitle":"Handle more error cases","messageBody":"","tags":["A-Jar"],"fileTypesAndContributionMap":{"java":{"insertions":25,"deletions":7}}}]},{"date":"2021-09-16","commitResults":[{"hash":"ad340f1bc3c385bf2dcd932d9222ae64d9b456e9","messageTitle":"Change data file separator and handle more data file parsing errors","messageBody":"","fileTypesAndContributionMap":{"java":{"insertions":11,"deletions":1}}}]},{"date":"2021-09-25","commitResults":[{"hash":"c36b30f1d1cbe05dfd7224b0dfd429676aefe915","messageTitle":"Rename Todo class to ToDo","messageBody":"","fileTypesAndContributionMap":{"java":{"insertions":6,"deletions":6}}},{"hash":"11dcbeaba3c52dc671b9e9f7e91a6b8c5593880b","messageTitle":"Conform to coding standard","messageBody":"","fileTypesAndContributionMap":{"java":{"insertions":1,"deletions":1}}}]},{"date":"2021-09-27","commitResults":[{"hash":"3643282898283813cc8a6083bf2815366efd67e0","messageTitle":"Refactor storage methods into Storage class","messageBody":"","fileTypesAndContributionMap":{"java":{"insertions":172,"deletions":117}}},{"hash":"00a3e4967a15f7f2d2650e26287f190a0ad66462","messageTitle":"Create and use TaskList class","messageBody":"","fileTypesAndContributionMap":{"java":{"insertions":53,"deletions":17}}},{"hash":"4c2ac92f2ebc2227e10c04c025c83b7ab66f91e8","messageTitle":"Refactor print methods into Ui class","messageBody":"","fileTypesAndContributionMap":{"java":{"insertions":59,"deletions":58}}},{"hash":"87c77753efcd5fb805694470e988a5ad34cf9a40","messageTitle":"Replace System.lineSeparator() with new line character","messageBody":"","fileTypesAndContributionMap":{"java":{"insertions":4,"deletions":6}}},{"hash":"7826230f3b05a595415b34d158075f966b56050a","messageTitle":"Refactor Duke class to use non-static methods","messageBody":"","fileTypesAndContributionMap":{"java":{"insertions":26,"deletions":20}}},{"hash":"d87007cb1e26e27445000ca873bc08d735d8aa81","messageTitle":"Create Parser class and use regex match groups for parsing","messageBody":"","fileTypesAndContributionMap":{"java":{"insertions":84,"deletions":44}}},{"hash":"35a0e8b980bddeb06ac5c6b249f824a386f85e1f","messageTitle":"Implement Command classes","messageBody":"","fileTypesAndContributionMap":{"java":{"insertions":175,"deletions":0}}},{"hash":"80dfce6c1b779197f8070d1eca3ec4a9b1e39358","messageTitle":"Move getUserInput() to Ui class","messageBody":"","fileTypesAndContributionMap":{"java":{"insertions":17,"deletions":5}}},{"hash":"f53ec83d4103737f310ef0a212d6a93e5b9ffbec","messageTitle":"Move parsing methods into Parser class and integrate Command classes","messageBody":"","fileTypesAndContributionMap":{"java":{"insertions":114,"deletions":179}}},{"hash":"0475201d291e401817329bf99c1856363a9c9177","messageTitle":"Remove extra brace","messageBody":"","fileTypesAndContributionMap":{"java":{"insertions":0,"deletions":1}}}]},{"date":"2021-09-29","commitResults":[{"hash":"603b7c006e92594ef2b69c8d2f8a33aa531e117a","messageTitle":"Add JavaDoc comments","messageBody":"","fileTypesAndContributionMap":{"java":{"insertions":174,"deletions":41}}},{"hash":"7080948496b9ebe538545304d369c1e18028dff8","messageTitle":"Modify encoding/decoding methods in Storage to use different format.","messageBody":"Overlaps with the format used by Parser.\n","fileTypesAndContributionMap":{"java":{"insertions":110,"deletions":73}}},{"hash":"965d79389bae6d06f8c5f1723b84707b84e7ff63","messageTitle":"Replace string literal with constant","messageBody":"","tags":["A-MoreOOP"],"fileTypesAndContributionMap":{"java":{"insertions":4,"deletions":3}}}]}]},"authorFileTypeContributionMap":{"bernardboey":{"java":956,"md":0,"fxml":0,"sh":7,"bat":5,"gradle":0,"txt":26}},"authorContributionVariance":{"bernardboey":6458.168},"authorDisplayNameMap":{"bernardboey":"CS2113-T16-3 BERN..CHEN"}}
